rl_rocket_sim/__init__.py
rl_rocket_sim/envs/__init__.py
rl_rocket_sim/envs/rocket_env.py
rl_rocket_sim/envs/rocket_env_fins.py
rl_rocket_sim/utils/simulator.py
rl_rocket_sim/wrappers/__init__.py
rl_rocket_sim/wrappers/wrappers.py
rl_rocket_sim-0.0.3.dist-info/LICENSE
rl_rocket_sim-0.0.3.dist-info/WHEEL
rl_rocket_sim-0.0.3.dist-info/METADATA
rl_rocket_sim-0.0.3.dist-info/RECORD
