Metadata-Version: 2.1
Name: rl_rocket_sim
Version: 0.0.3
Summary: A Gym-compatible rocket simulator.
Author-email: Davide Iafrate <dvd.iafrate98@gmail.com>
Classifier: License :: OSI Approved :: MIT License
Project-URL: Home, https://github.com/Tuxliri/rocket-sim
